standup_face_recognition2/Facebox_detector.py
standup_face_recognition2/MTCNN_detector.py
standup_face_recognition2/__init__.py
standup_face_recognition2/face_recognition.py
standup_face_recognition2/main.py
standup_face_recognition2/pedestrian_detector.py
standup_face_recognition2/team_embedding_webcam_faceboxes_casia.pth
standup_face_recognition2/team_embedding_webcam_faceboxes_vgg.pth
standup_face_recognition2/team_embedding_webcam_mtcnn_casia.pth
standup_face_recognition2/team_embedding_webcam_mtcnn_vgg.pth
standup_face_recognition2/utils.py
standup_face_recognition2/faceboxes/FaceBoxes.pth
standup_face_recognition2/faceboxes/__init__.py
standup_face_recognition2/faceboxes/box_utils.py
standup_face_recognition2/faceboxes/config.py
standup_face_recognition2/faceboxes/faceboxes.py
standup_face_recognition2/faceboxes/helper.py
standup_face_recognition2/faceboxes/prior_box.py
standup_face_recognition2/facenet_pytorch/__init__.py
standup_face_recognition2/facenet_pytorch/test.py
standup_face_recognition2/facenet_pytorch/data/__init__.py
standup_face_recognition2/facenet_pytorch/data/onet.pt
standup_face_recognition2/facenet_pytorch/data/pnet.pt
standup_face_recognition2/facenet_pytorch/data/rnet.pt
standup_face_recognition2/facenet_pytorch/models/__init__.py
standup_face_recognition2/facenet_pytorch/models/inception_resnet_v1.py
standup_face_recognition2/facenet_pytorch/models/mtcnn.py
standup_face_recognition2/facenet_pytorch/models/utils/__init__.py
standup_face_recognition2/facenet_pytorch/models/utils/detect_face.py
standup_face_recognition2/facenet_pytorch/models/utils/download.py
standup_face_recognition2/facenet_pytorch/models/utils/tensorflow2pytorch.py
standup_face_recognition2/facenet_pytorch/models/utils/training.py
standup_face_recognition2-0.7.dist-info/METADATA
standup_face_recognition2-0.7.dist-info/WHEEL
standup_face_recognition2-0.7.dist-info/entry_points.txt
standup_face_recognition2-0.7.dist-info/top_level.txt
standup_face_recognition2-0.7.dist-info/RECORD
